{
  "project_info": {
    "project_number": "645368796596",
    "project_id": "char-app2-aa579",
    "storage_bucket": "char-app2-aa579.appspot.com"
  },
  "client": [
    {
      "client_info": {
        "mobilesdk_app_id": "1:645368796596:android:525e4c99f5ef1b6922cee1",
        "android_client_info": {
          "package_name": "com.example.charapp2"
        }
      },
      "oauth_client": [
        {
          "client_id": "645368796596-rfb5pt5p6al8cd657qr0m4hrm8i46efs.apps.googleusercontent.com",
          "client_type": 1,
          "android_info": {
            "package_name": "com.example.charapp2",
            "certificate_hash": "31e9c7248114303eb2f4f22a21ac483304a27c2c"
          }
        },
        {
          "client_id": "645368796596-t2pihp8gari3g88iss58ldjnkag47etb.apps.googleusercontent.com",
          "client_type": 3
        }
      ],
      "api_key": [
        {
          "current_key": "AIzaSyD5vQ82mzziIVxqnh2pe4qhjbusaeXN7eI"
        }
      ],
      "services": {
        "appinvite_service": {
          "other_platform_oauth_client": [
            {
              "client_id": "645368796596-t2pihp8gari3g88iss58ldjnkag47etb.apps.googleusercontent.com",
              "client_type": 3
            }
          ]
        }
      }
    }
  ],
  "configuration_version": "1"
}